pyfake/__init__.py
pyfake/exceptions.py
pyfake/schemas.py
pyfake/settings.py
pyfake/core/api.py
pyfake/core/context.py
pyfake/core/engine.py
pyfake/core/registry.py
pyfake/generators/datetime.py
pyfake/generators/primitives.py
pyfake/generators/uuid.py
pyfake-0.0.6.dist-info/licenses/LICENSE
pyfake-0.0.6.dist-info/METADATA
pyfake-0.0.6.dist-info/WHEEL
pyfake-0.0.6.dist-info/top_level.txt
pyfake-0.0.6.dist-info/RECORD
