Metadata-Version: 2.4
Name: pyfake
Version: 0.0.6
Summary: A fake data generator that is pydantic compatible.
Author-email: Pranesh Mukhopadhyay <praneshmukherjee7@gmail.com>
License: MIT
Keywords: pydantic,fake data,data generation,data validation,data modeling
Classifier: Intended Audience :: Information Technology
Classifier: Operating System :: OS Independent
Classifier: Programming Language :: Python :: 3
Classifier: Programming Language :: Python
Classifier: Framework :: Pydantic
Classifier: Framework :: Pydantic :: 2
Classifier: Intended Audience :: Developers
Requires-Python: >=3.9
License-File: LICENSE
Requires-Dist: pydantic[email,timezone]>=2.12.5
Dynamic: license-file
